cvsvc_apirisk/__init__.py
cvsvc_apirisk/cvapirisk_pkg/API_Risk_Assessment_OB.pdf
cvsvc_apirisk/cvapirisk_pkg/CloudVector-APIRiskTool-Documentation.pdf
cvsvc_apirisk/cvapirisk_pkg/cv_rules_sample.json
cvsvc_apirisk/cvapirisk_pkg/example_cmds.txt
cvsvc_apirisk/cvapirisk_pkg/orangebank.zip
cvsvc_apirisk/cvapirisk_pkg/orangebank_user.json
cvsvc_apirisk/cvapirisk_pkg/orangebank_user_orig.json
cvsvc_apirisk/score/__init__.py
cvsvc_apirisk/score/base.py
cvsvc_apirisk/score/spec_security/__init__.py
cvsvc_apirisk/score/spec_security/apisparc_server.cfg
cvsvc_apirisk/score/spec_security/cv_apirisk_assessment.py
cvsvc_apirisk/score/spec_security/cv_apirisk_server.py
cvsvc_apirisk/score/spec_security/json_line.py
cvsvc_apirisk/score/spec_security/sps_common.py
cvsvc_apirisk/score/spec_security/sps_main.py
cvsvc_apirisk/score/spec_security/sps_main_cr.py
cvsvc_apirisk/score/spec_security/sps_spec_util.py
cvsvc_apirisk/score/spec_security/data_attrs/__init__.py
cvsvc_apirisk/score/spec_security/data_attrs/sps_data_attr01.py
cvsvc_apirisk/score/spec_security/data_attrs/sps_data_attr02.py
cvsvc_apirisk/score/spec_security/data_attrs/sps_data_attr03.py
cvsvc_apirisk/score/spec_security/data_attrs/sps_data_attr04.py
cvsvc_apirisk/score/spec_security/data_attrs/sps_data_attr05.py
cvsvc_apirisk/score/spec_security/data_attrs/sps_data_attr06.py
cvsvc_apirisk/score/spec_security/data_attrs/sps_data_attr07.py
cvsvc_apirisk/score/spec_security/data_attrs/sps_data_attr08.py
cvsvc_apirisk/score/spec_security/data_attrs/sps_data_attr09.py
cvsvc_apirisk/score/spec_security/data_attrs/sps_data_attr10.py
cvsvc_apirisk/score/spec_security/data_attrs/sps_data_attr11.py
cvsvc_apirisk/score/spec_security/data_attrs/sps_data_attr12.py
cvsvc_apirisk/score/spec_security/fmt_attrs/__init__.py
cvsvc_apirisk/score/spec_security/fmt_attrs/sps_fmt_attr01.py
cvsvc_apirisk/score/spec_security/fmt_attrs/sps_fmt_attr02.py
cvsvc_apirisk/score/spec_security/fmt_attrs/sps_fmt_attr03.py
cvapirisk-1.2.12.dist-info/LICENSE
cvapirisk-1.2.12.dist-info/METADATA
cvapirisk-1.2.12.dist-info/WHEEL
cvapirisk-1.2.12.dist-info/entry_points.txt
cvapirisk-1.2.12.dist-info/top_level.txt
cvapirisk-1.2.12.dist-info/RECORD
