Metadata-Version: 2.1
Name: cvapirisk
Version: 1.2.12
Summary: API Specification Analysis for Risks and Compliance
Author: CloudVector
Author-email: support@cloudvector.com
License: UNKNOWN
Platform: UNKNOWN
Classifier: Programming Language :: Python :: 3
Classifier: Operating System :: OS Independent
Requires-Python: >=3
License-File: LICENSE
Requires-Dist: MarkupSafe (==2.0.1)
Requires-Dist: openapi-spec-validator (==0.2.9)
Requires-Dist: openapi3 (==1.0.0)
Requires-Dist: prance (==0.19.0)
Requires-Dist: numpy (==1.22.3)
Requires-Dist: networkx (==2.4)
Requires-Dist: parsimonious (==0.8.1)
Requires-Dist: sanic (==20.3.0)
Requires-Dist: jinja2 (==3.0.3)
